MANIFEST.in
setup.py
seed/CHeck
seed/__init__.py
seed/__pycache__/__init__.cpython-36.pyc
seed/mrclients/__init__.py
seed/mrclients/build.sh
seed/mrclients/controll.py
seed/mrclients/default_firewall.txt
seed/mrclients/__pycache__/__init__.cpython-36.pyc
seed/mrclients/__pycache__/controll.cpython-36.pyc
seed/mrpackage/__init__.py
seed/mrpackage/api.py
seed/mrpackage/config.py
seed/mrpackage/daemon.py
seed/mrpackage/libs.py
seed/mrpackage/oscmd.py
seed/mrpackage/services.py
seed/mrpackage/test.py
seed/mrpackage/udp.py
seed/mrpackage/__pycache__/__init__.cpython-36.pyc
seed/mrpackage/__pycache__/api.cpython-36.pyc
seed/mrpackage/__pycache__/config.cpython-36.pyc
seed/mrpackage/__pycache__/daemon.cpython-36.pyc
seed/mrpackage/__pycache__/libs.cpython-36.pyc
seed/mrpackage/__pycache__/oscmd.cpython-36.pyc
seed/mrpackage/__pycache__/services.cpython-36.pyc
seed/mrpackage/__pycache__/test.cpython-36.pyc
seed/mrpackage/__pycache__/udp.cpython-36.pyc
seed/mrservers/__init__.py
seed/mrservers/local.py
seed/mrservers/test_server.py
seed/mrservers/__pycache__/__init__.cpython-36.pyc
seed/mrservers/__pycache__/local.cpython-36.pyc
seed/utils/__init__.py
seed/utils/display.py
seed/utils/__pycache__/__init__.cpython-36.pyc
x_mroy_1046.egg-info/PKG-INFO
x_mroy_1046.egg-info/SOURCES.txt
x_mroy_1046.egg-info/dependency_links.txt
x_mroy_1046.egg-info/entry_points.txt
x_mroy_1046.egg-info/not-zip-safe
x_mroy_1046.egg-info/requires.txt
x_mroy_1046.egg-info/top_level.txt