Metadata-Version: 1.0
Name: x-mroy-1046
Version: 0.2.6
Summary: a anayzer package
Home-page: https://github.com/Qingluan/.git
Author: Qing luan
Author-email: darkhackdevil@gmail.com
License: MIT
Platform: UNKNOWN
